{
  "nzsl_id": 3140,
  "gloss": {
    "english": [
      "island"
    ],
    "english_secondary": [
      ""
    ],
    "maori": [
      "motu"
    ],
    "attributes": [
      "noun"
    ]
  },
  "video": "island.3140.main_glosses.mb.r480x360.mp4",
  "usage": [
    {
      "video": "island.3140.finalexample1.mb.r480x360.mp4",
      "signs": [
        2879,
        859,
        2299,
        5752,
        3140,
        402,
        2583,
        5617,
        5391
      ],
      "translation": "We caught a boat to a small island and camped there for two nights."
    }
  ],
  "attributes": {
    "handshapes": [
      "handshape.4.3.1-1558aa1bdc1bf7e2a85642d1f2313aa0229fea8cf6bed2430a9bd38672fd2976.png"
    ],
    "locations": [
      "location.1.1.in_front_of_body-9dd4eb3a77c2bc0fc515de633c0b0cc4d5b11fb1cabcb2d5578dc9d7a8b03ff2.png"
    ]
  },
  "image": "island-3140.png"
}