{
  "nzsl_id": 3224,
  "gloss": {
    "english": [
      "axe"
    ],
    "english_secondary": [
      "chop"
    ],
    "maori": [
      "toki"
    ],
    "attributes": [
      "noun",
      "verb"
    ]
  },
  "video": "axe.3224.main_glosses.mb.r480x360.mp4",
  "usage": [
    {
      "video": "axe.3224.finalexample1.mb.r480x360.mp4",
      "signs": [
        2556,
        4266,
        3224,
        1185,
        5533,
        946
      ],
      "translation": "I borrowed an axe. I needed to chop some wood."
    }
  ],
  "attributes": {
    "handshapes": [
      "handshape.3.3.1-d18f27d6d81099e10a6218bc2ddbe4ec593c7af02265d63b9b6b6df1764d8630.png"
    ],
    "locations": [
      "location.1.1.in_front_of_body-9dd4eb3a77c2bc0fc515de633c0b0cc4d5b11fb1cabcb2d5578dc9d7a8b03ff2.png"
    ]
  },
  "image": "axe-3224.png"
}