{
  "nzsl_id": 5229,
  "gloss": {
    "english": [
      "that's right"
    ],
    "english_secondary": [
      ""
    ],
    "maori": [
      "e tika ana"
    ],
    "attributes": [
      "interjection"
    ]
  },
  "video": "thats_right.5229.main_glosses.sp.r480x360.mp4",
  "usage": [
    {
      "video": "thats_right.5229.finalexample1.sp.r480x360.mp4",
      "signs": [
        5229,
        2556,
        1376,
        3524,
        2556,
        4006,
        1015,
        1071
      ],
      "translation": "That's right, I forgot all about the appointment. Thanks for reminding me."
    }
  ],
  "attributes": {
    "handshapes": [
      "handshape.3.1.1-05f350e971e1e1b531fe1933540356df1186933bcd0a76d05c96c82ff55a650e.png"
    ],
    "locations": [
      "location.1.1.in_front_of_body-9dd4eb3a77c2bc0fc515de633c0b0cc4d5b11fb1cabcb2d5578dc9d7a8b03ff2.png"
    ]
  },
  "image": "that_s_right-5229.png"
}