{
  "nzsl_id": 557,
  "gloss": {
    "english": [
      "progress"
    ],
    "english_secondary": [
      "advance",
      "headway",
      "make progress"
    ],
    "maori": [
      "ahu whakamua",
      "kauneke"
    ],
    "attributes": [
      "verb"
    ]
  },
  "video": "progress.557.main_glosses.vs.r480x360.mp4",
  "usage": [
    {
      "video": "progress.557.finalexample1.vs.r480x360.mp4",
      "signs": [
        4656,
        5844,
        557,
        3684,
        908,
        4130,
        1279
      ],
      "translation": "Accessibility for deaf people has progressed. It's better now than it used to be."
    }
  ],
  "attributes": {
    "handshapes": [
      "handshape.1.1.1-f5d9aca796fcb8a045553fa69be32b9a3f2cb2abcbe9639923f8a00189ea3da8.png"
    ],
    "locations": [
      "location.1.1.in_front_of_body-9dd4eb3a77c2bc0fc515de633c0b0cc4d5b11fb1cabcb2d5578dc9d7a8b03ff2.png"
    ]
  },
  "image": "progress-557.png"
}