{
  "nzsl_id": 5608,
  "gloss": {
    "english": [
      "eleven"
    ],
    "english_secondary": [
      "11"
    ],
    "maori": [
      "tekau mā tahi"
    ],
    "attributes": [
      "numeral"
    ]
  },
  "video": "eleven.5608.main_glosses.mb.r480x360.mp4",
  "usage": [
    {
      "video": "eleven.5608.finalexample1.mb.r480x360.mp4",
      "signs": [
        2556,
        4573,
        5608,
        3111,
        1031,
        1463,
        6230,
        5609
      ],
      "translation": "I fly out at eleven in the morning and arrive there around half past twelve."
    }
  ],
  "attributes": {
    "handshapes": [
      "handshape.6.1.1-e3e3a4005fafd87816d6721fd3a66539ec8195715f551f3bc72e1424e3268132.png"
    ],
    "locations": [
      "location.1.1.in_front_of_body-9dd4eb3a77c2bc0fc515de633c0b0cc4d5b11fb1cabcb2d5578dc9d7a8b03ff2.png"
    ]
  },
  "image": "eleven-5608.png"
}