{
  "nzsl_id": 5789,
  "gloss": {
    "english": [
      "friend"
    ],
    "english_secondary": [
      "companion",
      "friendly",
      "friendship"
    ],
    "maori": [
      "hoa"
    ],
    "attributes": [
      "noun"
    ]
  },
  "video": "friend.5789.main_glosses.sp.r480x360.mp4",
  "usage": [
    {
      "video": "friend.5789.finalexample1.sp.r480x360.mp4",
      "signs": [
        2879,
        3658,
        1083,
        959,
        2879
      ],
      "translation": "We're good friends. We grew up together."
    }
  ],
  "attributes": {
    "handshapes": [
      "handshape.3.2.1-c7492f52cdbdc01778e01991cd55de007fd039bc0454716ec3c59d56ca49c998.png"
    ],
    "locations": [
      "location.1.1.in_front_of_body-9dd4eb3a77c2bc0fc515de633c0b0cc4d5b11fb1cabcb2d5578dc9d7a8b03ff2.png"
    ]
  },
  "image": "friend-5789.png"
}